itelegram/__init__.py
itelegram/admin.py
itelegram/apps.py
itelegram/bot.py
itelegram/decorators.py
itelegram/defaults.py
itelegram/managers.py
itelegram/models.py
itelegram/mqbot.py
itelegram/services.py
itelegram/urls.py
itelegram/views.py
itelegram/management/__init__.py
itelegram/management/commands/__init__.py
itelegram/management/commands/botpolling.py
itelegram/migrations/0001_initial.py
itelegram/migrations/0002_auto_20201114_1955.py
itelegram/migrations/__init__.py
itelegram/static/css/django_telegrambot.css
itelegram/static/img/.gitignore
itelegram/static/img/iTelegram.png
itelegram/static/js/django_telegrambot.js
itelegram/templates/itelegram/base.html
itelegram/templates/itelegram/index.html
django_itelegram-1.2.6.dist-info/LICENSE
django_itelegram-1.2.6.dist-info/METADATA
django_itelegram-1.2.6.dist-info/WHEEL
django_itelegram-1.2.6.dist-info/top_level.txt
django_itelegram-1.2.6.dist-info/RECORD
