Metadata-Version: 2.1
Name: django-itelegram
Version: 1.2.6
Summary: Developing Telegram bots on Django with extra built-in features
Home-page: https://github.com/YazdanRa/django-itelegram
Author: Yazdan Ranjbar
License: MIT
Download-URL: https://pypi.python.org/pypi/django-itelegram
Platform: UNKNOWN
Classifier: Development Status :: 5 - Production/Stable
Classifier: Environment :: Web Environment
Classifier: Framework :: Django
Classifier: Framework :: Django :: 3.0
Classifier: Framework :: Django :: 3.1
Classifier: Intended Audience :: Developers
Classifier: License :: OSI Approved :: MIT License
Classifier: Operating System :: OS Independent
Classifier: Programming Language :: Python
Classifier: Programming Language :: Python :: 3.6
Classifier: Programming Language :: Python :: 3.7
Classifier: Programming Language :: Python :: 3.8
Classifier: Programming Language :: Python :: 3.9
Requires-Dist: Django (>=3.0)
Requires-Dist: python-telegram-bot (>=13.0)
Provides-Extra: dev
Requires-Dist: black ; extra == 'dev'
Requires-Dist: pre-commit ; extra == 'dev'
Requires-Dist: psycopg2-binary ; extra == 'dev'
